.DS_Store
slot_ZC/Bi_model.py
slot_ZC/__init__.py
slot_ZC/config.json
slot_ZC/config.py
slot_ZC/data2index_ver2.py
slot_ZC/make_dict.py
slot_ZC/model.py
slot_ZC/predict.py
slot_ZC/run.py
slot_ZC/test
slot_ZC/train.py
slot_ZC/train_dev
slot_ZC/utils.py
slot_ZC/vocab.intent
slot_ZC/vocab.slot
slot_ZC/cli/__init__.py
slot_ZC/cli/predict.py
slot_ZC/cli/train.py
slot_filling_ZC-0.2.4.dist-info/LICENSE
slot_filling_ZC-0.2.4.dist-info/METADATA
slot_filling_ZC-0.2.4.dist-info/WHEEL
slot_filling_ZC-0.2.4.dist-info/top_level.txt
slot_filling_ZC-0.2.4.dist-info/RECORD
