Metadata-Version: 2.1
Name: slot-filling-ZC
Version: 0.2.4
Summary: train(train_file,test_file,vocab_intent_file,vocab_slot_file)
Home-page: UNKNOWN
Author: Zichu
Author-email: zichuu@gwu.edu
License: UNKNOWN
Platform: UNKNOWN
Classifier: Programming Language :: Python :: 3
Classifier: License :: OSI Approved :: MIT License
Classifier: Operating System :: OS Independent
License-File: LICENSE
